mux4x1/rtl/mux4x1.v
`timescale 1ns / 1ps

module mux4x1(i_sel,
              i_a,
              i_b,
              i_c,
              i_d,
              o_data);

parameter data_width = 32;

input [data_width-1 : 0] i_a;
input [data_width-1 : 0] i_b;
input [data_width-1 : 0] i_c;
input [data_width-1 : 0] i_d;
input [1:0] i_sel;

output reg [data_width-1 : 0] o_data;

always @ (*) begin
    case(i_sel) 
    2'b00 : o_data = i_a;
    2'b01 : o_data = i_b;
    2'b10 : o_data = i_c;
    2'b11 : o_data = i_d;
    default: o_data = 32'b0;
    endcase

end
endmodule

mul_4/rtl/mul4.v
`timescale 1ns / 1ps
module mul4(i_data,
            o_data);

parameter width_in = 32;
parameter width_out = 32;

input [width_in-1:0] i_data;
output wire [width_out-1:0] o_data;

assign o_data = i_data<<2;

endmodule

dff_en/rtl/dff_en.v
`timescale 1ns / 1ps

module dff_en(i_clk,
              i_en,
              i_reset,
              i_data,
              o_data);


input i_clk;
input i_reset;
input i_en;
input [31:0] i_data;

output reg [31:0] o_data;

always @ (posedge i_clk)begin
    if (i_reset == 1'b1) begin
        o_data <= 32'b0;
    end else begin
        if (i_en == 1'b1)  
            o_data <= i_data;
    end
end

endmodule

alu/rtl/alu.v
`timescale 1ns / 1ps

module alu(i_in1,
           i_in2,
           i_op,
           o_zero,
           o_data);

parameter DATA_WIDTH = 32;
parameter OP_WIDTH = 3;

parameter AND  = 3'b000;
parameter OR   = 3'b001;
parameter ADD  = 3'b010;
parameter NOP  = 3'b011;
parameter NOR = 3'b100;
parameter XOR  = 3'b101;
parameter SUB  = 3'b110;
parameter SLT  = 3'b111;

input [DATA_WIDTH-1:0] i_in1;
input [DATA_WIDTH-1:0] i_in2;
input [OP_WIDTH-1:0] i_op;

output reg [DATA_WIDTH-1:0] o_data;
output wire o_zero;

always @ (*) begin
    case(i_op)
    AND   : o_data = i_in1 & i_in2;
    OR    : o_data = i_in1 | i_in2;
    ADD   : o_data = i_in1 + i_in2;
    NOP   : o_data = 32'b0;
    NOR   : o_data = ~(i_in1|i_in2);
    XOR   : o_data = i_in1 ^ i_in2;
    SUB   : o_data = i_in1 - i_in2;
    SLT   : o_data = ($signed(i_in1) < $signed(i_in2)) ? {{(DATA_WIDTH-1){1'b0}},1'b1} : {DATA_WIDTH{1'b0}};
    default : o_data = 32'b0;
    endcase
end

assign o_zero = (o_data == 32'b0 )? 1'b1 : 1'b0; 

endmodule

mux2x1/rtl/mux2x1.v
`timescale 1ns / 1ps
module mux2x1(i_a,
              i_b,
              i_sel,
              o_c);

parameter width_a = 32;
parameter width_b = 32;
parameter width_c = 32;

input [width_a-1:0] i_a;
input [width_b-1:0] i_b;
input i_sel;

output wire [width_c-1:0] o_c;

assign o_c = i_sel ? i_b : i_a;

endmodule

sign_imm/rtl/sign_imm.v
`timescale 1ns / 1ps


module sign_imm(i_data,
                o_imm);


input [15:0] i_data;

output wire [31:0] o_imm;

assign o_imm = {{16{i_data[15]}}, i_data};

endmodule

register_file/rtl/register_file.v
`timescale 1ns / 1 ps

module register_file(i_clk,
                     i_a1,  //address 1
                     i_a2,  //address 2
                     i_a3,  //address 3 /data
                     i_wd3, //write data3 32 bit
                     i_we3, //enable write of reg
                     o_rd1, //read data 1
                     o_rd2  //read data 2
                    );

input i_clk;
input [4:0] i_a1; //to address 32x32bit register (5 bits = 32)
input [4:0] i_a2;
input [4:0] i_a3;
input [31:0] i_wd3; //write data input for 32 bit reg
input i_we3;

output wire [31:0] o_rd1; //output wrte data1
output wire [31:0] o_rd2; //output wite data2


reg [31:0] internal_reg_file [31:0]; //32 x 32 bit registers for storage of instruction/data

always @ (posedge i_clk) begin

    if(i_we3 == 1'b1) begin
        internal_reg_file[i_a3] <= i_wd3;
    end
end

assign o_rd1 = internal_reg_file[i_a1];
assign o_rd2 = internal_reg_file[i_a2];

endmodule

inst_data_memory/rtl/inst_data_memory.v
`timescale 1ns / 1ps

module inst_data_memory(i_clk,
                        i_addr,
                        i_we, 
                        i_wdata,
                        o_rdata);

input i_clk;
input i_we;
input [31:0] i_addr;
input [31:0] i_wdata;

output wire [31:0] o_rdata;

parameter depth_inst = 256;
parameter depth_data = 256;

wire [8:0] masked_addr;
reg [31:0] inst_mem [depth_inst-1:0];
reg [31:0] data_mem [depth_data-1:0];

assign masked_addr = i_addr[10:2];

always @ (posedge i_clk) begin
    if (i_we) begin
         if (masked_addr[8] == 1'b1) 
                data_mem[masked_addr[7:0]] <= i_wdata;
         else  
                inst_mem[masked_addr[7:0]] <= i_wdata;
    end

end

assign o_rdata =  (masked_addr[8]==1'b1) ? data_mem[masked_addr[7:0]] : inst_mem[masked_addr[7:0]];

endmodule

datapath/rtl/datapath.v
`timescale 1ns / 1ps

module datapath(i_clk,
                i_iord,
                i_memwrite,
                i_irwrite,
                i_regdst,
                i_memtoreg,
                i_regwrite,
                i_alusrca,
                i_alusrcb,
                i_aluctrl,
                i_pcsrc,
                i_branch,
                i_pcwrite,
                i_reset,
                o_operand,
                o_func);

input i_clk;

input i_iord;
input i_memwrite;
input i_irwrite;

input i_regdst;
input i_memtoreg;
input i_regwrite;

input i_alusrca;
input [1:0] i_alusrcb;
input [2:0] i_aluctrl;

input [1:0] i_pcsrc;
input i_branch;
input i_pcwrite;

input i_reset;

output wire [5:0] o_operand;
output wire [5:0]  o_func;


wire [31:0] pc_value;
wire [31:0] alu_out;
wire [31:0] Adr;

wire [31:0] data;

wire [31:0] w_data;
wire [31:0] o_rdata;

wire [31:0] instr;

wire [4:0] address3;
wire [31:0] data3;

wire [31:0] data_a;
wire [31:0] data_b;

wire [31:0] o_data_a;
wire [31:0] o_data_b;

wire [31:0] signimm;

wire [31:0] shift_value;

wire [31:0] srca;

wire [31:0] srcb;

wire set_zero;
wire [31:0] alu_result;

wire res_branch;

wire pc_en;

wire [27:0] jump_value;

wire [31:0] new_pcvalue;

//Pc register
dff_en pc_reg(.i_clk(i_clk), 
              .i_en(pc_en), 
              .i_reset(i_reset), 
              .i_data(new_pcvalue), 
              .o_data(pc_value));

//mux after PC
mux2x1 #(.width_a(32), .width_b(32), .width_c(32)) i_d_mux(.i_a(pc_value), 
                                                           .i_b(alu_out),
                                                           .o_c(Adr), 
                                                           .i_sel(i_iord));

//inst and data memory
inst_data_memory #(.depth_inst(256), .depth_data(256)) inst_data_mem(.i_clk(i_clk), 
                                                                     .i_addr(Adr), 
                                                                     .i_we(i_memwrite), 
                                                                     .i_wdata(o_data_b), 
                                                                     .o_rdata(o_rdata));

//DFF for instruction
dff_en inst_reg(.i_clk(i_clk), 
                .i_en(i_irwrite), 
                .i_reset(i_reset), 
                .i_data(o_rdata), 
                .o_data(instr));

//always enabled Data DFF
dff_en data_reg(.i_clk(i_clk), 
                .i_en(1'b1), 
                .i_reset(i_reset), 
                .i_data(o_rdata), 
                .o_data(data));

//register number rs. rt destination mux
mux2x1 #(.width_a(5), .width_b(5), .width_c(5)) regdst_mux(.i_a(instr[20:16]), 
                                                           .i_b(instr[15:11]), 
                                                           .o_c(address3), 
                                                           .i_sel(i_regdst));

//data mux alu, in sel mux
mux2x1 #(.width_a(32), .width_b(32), .width_c(32)) data_mux(.i_a(alu_out), 
                                                            .i_b(data), 
                                                            .o_c(data3), 
                                                            .i_sel(i_memtoreg));

//register unit of 32x32 register
register_file reg_unit(.i_clk(i_clk),
                       .i_a1(instr[25:21]),
                       .i_a2(instr[20:16]),
                       .i_a3(address3),
                       .i_wd3(data3),
                       .i_we3(i_regwrite),
                       .o_rd1(data_a),
                       .o_rd2(data_b));

//output a and b register to hold value originally 1 x 2in dff needed but we replace it 2 x 1in dff with same clock
//dff1
dff_en data_reg_a(.i_clk(i_clk), 
                 .i_en(1'b1), 
                 .i_reset(i_reset), 
                 .i_data(data_a), 
                 .o_data(o_data_a));

//dff2
dff_en data_reg_b(.i_clk(i_clk), 
                  .i_en(1'b1), 
                  .i_reset(i_reset), 
                  .i_data(data_b), 
                  .o_data(o_data_b));

//sign immedeate 
sign_imm sign_unit(.i_data(instr[15:0]),
                   .o_imm(signimm));

//multiplier
mul4 #(.width_in(32), .width_out(32)) shift2_pc(.i_data(signimm),
                                                .o_data(shift_value));

//ssource a mux
mux2x1 #(.width_a(32), .width_b(32), .width_c(32)) mux_a(.i_a(pc_value), 
                                                         .i_b(o_data_a), 
                                                         .o_c(srca), 
                                                         .i_sel(i_alusrca));

//source b mux
mux4x1 #(.data_width(32)) mux_b(.i_a(o_data_b),
                                .i_b(32'd4),
                                .i_c(signimm),
                                .i_d(shift_value),
                                .o_data(srcb),
                                .i_sel(i_alusrcb));

alu #(.DATA_WIDTH(32), .OP_WIDTH(3)) alu_i(.i_in1(srca),
                                           .i_in2(srcb),
                                           .i_op(i_aluctrl),
                                           .o_zero(set_zero),
                                           .o_data(alu_result));

and branch_and(res_branch, set_zero, i_branch);
or pcwrite_or(pc_en, res_branch, i_pcwrite);

dff_en alu_reg(.i_clk(i_clk), 
               .i_en(1'b1), 
               .i_reset(i_reset), 
               .i_data(alu_result), 
               .o_data(alu_out));

mul4 #(.width_in(26), .width_out(28)) shift2_jump(.i_data(instr[25:0]),
                                                  .o_data(jump_value));

mux4x1 #(.data_width(32)) mux_pc(.i_a(alu_result),
                                  .i_b(alu_out),
                                  .i_c({pc_value[31:28], jump_value}),
                                  .i_d(32'b1),
                                  .o_data(new_pcvalue),
                                  .i_sel(i_pcsrc));


assign o_operand = instr[31:26];
assign o_func = instr[5:0];

endmodule

datapath/dump.vcd
$version Generated by VerilatedVcd $end
$timescale 1ps $end
 $scope module $rootio $end
  $var wire 1 # i_clk $end
  $var wire 1 $ i_iord $end
  $var wire 1 % i_memwrite $end
  $var wire 1 & i_irwrite $end
  $var wire 1 ' i_regdst $end
  $var wire 1 ( i_memtoreg $end
  $var wire 1 ) i_regwrite $end
  $var wire 1 * i_alusrca $end
  $var wire 2 + i_alusrcb [1:0] $end
  $var wire 3 , i_aluctrl [2:0] $end
  $var wire 2 - i_pcsrc [1:0] $end
  $var wire 1 . i_branch $end
  $var wire 1 / i_pcwrite $end
  $var wire 1 0 i_reset $end
  $var wire 6 1 o_operand [5:0] $end
  $var wire 6 2 o_func [5:0] $end
 $upscope $end
 $scope module datapath $end
  $var wire 1 3 i_clk $end
  $var wire 1 4 i_iord $end
  $var wire 1 5 i_memwrite $end
  $var wire 1 6 i_irwrite $end
  $var wire 1 7 i_regdst $end
  $var wire 1 8 i_memtoreg $end
  $var wire 1 9 i_regwrite $end
  $var wire 1 : i_alusrca $end
  $var wire 2 ; i_alusrcb [1:0] $end
  $var wire 3 < i_aluctrl [2:0] $end
  $var wire 2 = i_pcsrc [1:0] $end
  $var wire 1 > i_branch $end
  $var wire 1 ? i_pcwrite $end
  $var wire 1 @ i_reset $end
  $var wire 6 A o_operand [5:0] $end
  $var wire 6 B o_func [5:0] $end
  $var wire 32 C pc_value [31:0] $end
  $var wire 32 D alu_out [31:0] $end
  $var wire 32 E Adr [31:0] $end
  $var wire 32 F data [31:0] $end
  $var wire 32 G w_data [31:0] $end
  $var wire 32 H o_rdata [31:0] $end
  $var wire 32 I instr [31:0] $end
  $var wire 5 J address3 [4:0] $end
  $var wire 32 K data3 [31:0] $end
  $var wire 32 L data_a [31:0] $end
  $var wire 32 M data_b [31:0] $end
  $var wire 32 N o_data_a [31:0] $end
  $var wire 32 O o_data_b [31:0] $end
  $var wire 32 P signimm [31:0] $end
  $var wire 32 Q shift_value [31:0] $end
  $var wire 32 R srca [31:0] $end
  $var wire 32 S srcb [31:0] $end
  $var wire 1 T set_zero $end
  $var wire 32 U alu_result [31:0] $end
  $var wire 1 V res_branch $end
  $var wire 1 W pc_en $end
  $var wire 28 X jump_value [27:0] $end
  $var wire 32 Y new_pcvalue [31:0] $end
  $scope module alu_i $end
   $var wire 32 o! DATA_WIDTH [31:0] $end
   $var wire 32 p! OP_WIDTH [31:0] $end
   $var wire 3 q! AND [2:0] $end
   $var wire 3 r! OR [2:0] $end
   $var wire 3 s! ADD [2:0] $end
   $var wire 3 t! NOP [2:0] $end
   $var wire 3 u! NOR [2:0] $end
   $var wire 3 v! XOR [2:0] $end
   $var wire 3 w! SUB [2:0] $end
   $var wire 3 x! SLT [2:0] $end
   $var wire 32 Z i_in1 [31:0] $end
   $var wire 32 [ i_in2 [31:0] $end
   $var wire 3 \ i_op [2:0] $end
   $var wire 32 ] o_data [31:0] $end
   $var wire 1 ^ o_zero $end
  $upscope $end
  $scope module alu_reg $end
   $var wire 1 _ i_clk $end
   $var wire 1 ` i_reset $end
   $var wire 1 a i_en $end
   $var wire 32 b i_data [31:0] $end
   $var wire 32 c o_data [31:0] $end
  $upscope $end
  $scope module data_mux $end
   $var wire 32 o! width_a [31:0] $end
   $var wire 32 o! width_b [31:0] $end
   $var wire 32 o! width_c [31:0] $end
   $var wire 32 d i_a [31:0] $end
   $var wire 32 e i_b [31:0] $end
   $var wire 1 f i_sel $end
   $var wire 32 g o_c [31:0] $end
  $upscope $end
  $scope module data_reg $end
   $var wire 1 h i_clk $end
   $var wire 1 i i_reset $end
   $var wire 1 j i_en $end
   $var wire 32 k i_data [31:0] $end
   $var wire 32 l o_data [31:0] $end
  $upscope $end
  $scope module data_reg_a $end
   $var wire 1 m i_clk $end
   $var wire 1 n i_reset $end
   $var wire 1 o i_en $end
   $var wire 32 p i_data [31:0] $end
   $var wire 32 q o_data [31:0] $end
  $upscope $end
  $scope module data_reg_b $end
   $var wire 1 r i_clk $end
   $var wire 1 s i_reset $end
   $var wire 1 t i_en $end
   $var wire 32 u i_data [31:0] $end
   $var wire 32 v o_data [31:0] $end
  $upscope $end
  $scope module i_d_mux $end
   $var wire 32 o! width_a [31:0] $end
   $var wire 32 o! width_b [31:0] $end
   $var wire 32 o! width_c [31:0] $end
   $var wire 32 w i_a [31:0] $end
   $var wire 32 x i_b [31:0] $end
   $var wire 1 y i_sel $end
   $var wire 32 z o_c [31:0] $end
  $upscope $end
  $scope module inst_data_mem $end
   $var wire 1 { i_clk $end
   $var wire 1 | i_we $end
   $var wire 32 } i_addr [31:0] $end
   $var wire 32 ~ i_wdata [31:0] $end
   $var wire 32 !! o_rdata [31:0] $end
   $var wire 32 y! depth_inst [31:0] $end
   $var wire 32 y! depth_data [31:0] $end
   $var wire 9 "! masked_addr [8:0] $end
  $upscope $end
  $scope module inst_reg $end
   $var wire 1 #! i_clk $end
   $var wire 1 $! i_reset $end
   $var wire 1 %! i_en $end
   $var wire 32 &! i_data [31:0] $end
   $var wire 32 '! o_data [31:0] $end
  $upscope $end
  $scope module mux_a $end
   $var wire 32 o! width_a [31:0] $end
   $var wire 32 o! width_b [31:0] $end
   $var wire 32 o! width_c [31:0] $end
   $var wire 32 (! i_a [31:0] $end
   $var wire 32 )! i_b [31:0] $end
   $var wire 1 *! i_sel $end
   $var wire 32 +! o_c [31:0] $end
  $upscope $end
  $scope module mux_b $end
   $var wire 32 o! data_width [31:0] $end
   $var wire 32 ,! i_a [31:0] $end
   $var wire 32 -! i_b [31:0] $end
   $var wire 32 .! i_c [31:0] $end
   $var wire 32 /! i_d [31:0] $end
   $var wire 2 0! i_sel [1:0] $end
   $var wire 32 1! o_data [31:0] $end
  $upscope $end
  $scope module mux_pc $end
   $var wire 32 o! data_width [31:0] $end
   $var wire 32 2! i_a [31:0] $end
   $var wire 32 3! i_b [31:0] $end
   $var wire 32 4! i_c [31:0] $end
   $var wire 32 5! i_d [31:0] $end
   $var wire 2 6! i_sel [1:0] $end
   $var wire 32 7! o_data [31:0] $end
  $upscope $end
  $scope module pc_reg $end
   $var wire 1 8! i_clk $end
   $var wire 1 9! i_reset $end
   $var wire 1 :! i_en $end
   $var wire 32 ;! i_data [31:0] $end
   $var wire 32 <! o_data [31:0] $end
  $upscope $end
  $scope module reg_unit $end
   $var wire 1 =! i_clk $end
   $var wire 5 >! i_a1 [4:0] $end
   $var wire 5 ?! i_a2 [4:0] $end
   $var wire 5 @! i_a3 [4:0] $end
   $var wire 32 A! i_wd3 [31:0] $end
   $var wire 1 B! i_we3 $end
   $var wire 32 C! o_rd1 [31:0] $end
   $var wire 32 D! o_rd2 [31:0] $end
   $var wire 32 E! internal_reg_file[0] [31:0] $end
   $var wire 32 F! internal_reg_file[1] [31:0] $end
   $var wire 32 G! internal_reg_file[2] [31:0] $end
   $var wire 32 H! internal_reg_file[3] [31:0] $end
   $var wire 32 I! internal_reg_file[4] [31:0] $end
   $var wire 32 J! internal_reg_file[5] [31:0] $end
   $var wire 32 K! internal_reg_file[6] [31:0] $end
   $var wire 32 L! internal_reg_file[7] [31:0] $end
   $var wire 32 M! internal_reg_file[8] [31:0] $end
   $var wire 32 N! internal_reg_file[9] [31:0] $end
   $var wire 32 O! internal_reg_file[10] [31:0] $end
   $var wire 32 P! internal_reg_file[11] [31:0] $end
   $var wire 32 Q! internal_reg_file[12] [31:0] $end
   $var wire 32 R! internal_reg_file[13] [31:0] $end
   $var wire 32 S! internal_reg_file[14] [31:0] $end
   $var wire 32 T! internal_reg_file[15] [31:0] $end
   $var wire 32 U! internal_reg_file[16] [31:0] $end
   $var wire 32 V! internal_reg_file[17] [31:0] $end
   $var wire 32 W! internal_reg_file[18] [31:0] $end
   $var wire 32 X! internal_reg_file[19] [31:0] $end
   $var wire 32 Y! internal_reg_file[20] [31:0] $end
   $var wire 32 Z! internal_reg_file[21] [31:0] $end
   $var wire 32 [! internal_reg_file[22] [31:0] $end
   $var wire 32 \! internal_reg_file[23] [31:0] $end
   $var wire 32 ]! internal_reg_file[24] [31:0] $end
   $var wire 32 ^! internal_reg_file[25] [31:0] $end
   $var wire 32 _! internal_reg_file[26] [31:0] $end
   $var wire 32 `! internal_reg_file[27] [31:0] $end
   $var wire 32 a! internal_reg_file[28] [31:0] $end
   $var wire 32 b! internal_reg_file[29] [31:0] $end
   $var wire 32 c! internal_reg_file[30] [31:0] $end
   $var wire 32 d! internal_reg_file[31] [31:0] $end
  $upscope $end
  $scope module regdst_mux $end
   $var wire 32 z! width_a [31:0] $end
   $var wire 32 z! width_b [31:0] $end
   $var wire 32 z! width_c [31:0] $end
   $var wire 5 e! i_a [4:0] $end
   $var wire 5 f! i_b [4:0] $end
   $var wire 1 g! i_sel $end
   $var wire 5 h! o_c [4:0] $end
  $upscope $end
  $scope module shift2_jump $end
   $var wire 32 {! width_in [31:0] $end
   $var wire 32 |! width_out [31:0] $end
   $var wire 26 i! i_data [25:0] $end
   $var wire 28 j! o_data [27:0] $end
  $upscope $end
  $scope module shift2_pc $end
   $var wire 32 o! width_in [31:0] $end
   $var wire 32 o! width_out [31:0] $end
   $var wire 32 k! i_data [31:0] $end
   $var wire 32 l! o_data [31:0] $end
  $upscope $end
  $scope module sign_unit $end
   $var wire 16 m! i_data [15:0] $end
   $var wire 32 n! o_imm [31:0] $end
  $upscope $end
 $upscope $end
$enddefinitions $end


#0
1#
0$
0%
0&
0'
0(
0)
0*
b00 +
b000 ,
b00 -
0.
0/
00
b000000 1
b000000 2
13
04
05
06
07
08
09
0:
b00 ;
b000 <
b00 =
0>
0?
0@
b000000 A
b000000 B
b00000000000000000000000000000000 C
b00000000000000000000000000000000 D
b00000000000000000000000000000000 E
b00000000000000000000000000000000 F
b00000000000000000000000000000000 G
b10001100001000100000000000000100 H
b00000000000000000000000000000000 I
b00000 J
b00000000000000000000000000000000 K
b00000000000000000000000000000000 L
b00000000000000000000000000000000 M
b00000000000000000000000000000000 N
b00000000000000000000000000000000 O
b00000000000000000000000000000000 P
b00000000000000000000000000000000 Q
b00000000000000000000000000000000 R
b00000000000000000000000000000000 S
1T
b00000000000000000000000000000000 U
0V
0W
b0000000000000000000000000000 X
b00000000000000000000000000000000 Y
b00000000000000000000000000000000 Z
b00000000000000000000000000000000 [
b000 \
b00000000000000000000000000000000 ]
1^
1_
0`
1a
b00000000000000000000000000000000 b
b00000000000000000000000000000000 c
b00000000000000000000000000000000 d
b00000000000000000000000000000000 e
0f
b00000000000000000000000000000000 g
1h
0i
1j
b10001100001000100000000000000100 k
b00000000000000000000000000000000 l
1m
0n
1o
b00000000000000000000000000000000 p
b00000000000000000000000000000000 q
1r
0s
1t
b00000000000000000000000000000000 u
b00000000000000000000000000000000 v
b00000000000000000000000000000000 w
b00000000000000000000000000000000 x
0y
b00000000000000000000000000000000 z
1{
0|
b00000000000000000000000000000000 }
b00000000000000000000000000000000 ~
b10001100001000100000000000000100 !!
b000000000 "!
1#!
0$!
0%!
b10001100001000100000000000000100 &!
b00000000000000000000000000000000 '!
b00000000000000000000000000000000 (!
b00000000000000000000000000000000 )!
0*!
b00000000000000000000000000000000 +!
b00000000000000000000000000000000 ,!
b00000000000000000000000000000100 -!
b00000000000000000000000000000000 .!
b00000000000000000000000000000000 /!
b00 0!
b00000000000000000000000000000000 1!
b00000000000000000000000000000000 2!
b00000000000000000000000000000000 3!
b00000000000000000000000000000000 4!
b00000000000000000000000000000001 5!
b00 6!
b00000000000000000000000000000000 7!
18!
09!
0:!
b00000000000000000000000000000000 ;!
b00000000000000000000000000000000 <!
1=!
b00000 >!
b00000 ?!
b00000 @!
b00000000000000000000000000000000 A!
0B!
b00000000000000000000000000000000 C!
b00000000000000000000000000000000 D!
b00000000000000000000000000000000 E!
b00000000000000000000000000000000 F!
b00000000000000000000000000000000 G!
b00000000000000000000000000000000 H!
b00000000000000000000000000000000 I!
b00000000000000000000000000000000 J!
b00000000000000000000000000000000 K!
b00000000000000000000000000000000 L!
b00000000000000000000000000000000 M!
b00000000000000000000000000000000 N!
b00000000000000000000000000000000 O!
b00000000000000000000000000000000 P!
b00000000000000000000000000000000 Q!
b00000000000000000000000000000000 R!
b00000000000000000000000000000000 S!
b00000000000000000000000000000000 T!
b00000000000000000000000000000000 U!
b00000000000000000000000000000000 V!
b00000000000000000000000000000000 W!
b00000000000000000000000000000000 X!
b00000000000000000000000000000000 Y!
b00000000000000000000000000000000 Z!
b00000000000000000000000000000000 [!
b00000000000000000000000000000000 \!
b00000000000000000000000000000000 ]!
b00000000000000000000000000000000 ^!
b00000000000000000000000000000000 _!
b00000000000000000000000000000000 `!
b00000000000000000000000000000000 a!
b00000000000000000000000000000000 b!
b00000000000000000000000000000000 c!
b00000000000000000000000000000000 d!
b00000 e!
b00000 f!
0g!
b00000 h!
b00000000000000000000000000 i!
b0000000000000000000000000000 j!
b00000000000000000000000000000000 k!
b00000000000000000000000000000000 l!
b0000000000000000 m!
b00000000000000000000000000000000 n!
b00000000000000000000000000100000 o!
b00000000000000000000000000000011 p!
b000 q!
b001 r!
b010 s!
b011 t!
b100 u!
b101 v!
b110 w!
b111 x!
b00000000000000000000000100000000 y!
b00000000000000000000000000000101 z!
b00000000000000000000000000011010 {!
b00000000000000000000000000011100 |!
#5000
0#
03
0_
0h
0m
0r
0{
0#!
08!
0=!
#10000
1#
13
b10001100001000100000000000000100 F
1_
b10001100001000100000000000000100 e
1h
b10001100001000100000000000000100 l
1m
1r
1{
1#!
18!
1=!
#15000
0#
03
0_
0h
0m
0r
0{
0#!
08!
0=!
#20000
1#
1&
b01 +
b010 ,
1/
13
16
b01 ;
b010 <
1?
b00000000000000000000000000000100 S
0T
b00000000000000000000000000000100 U
1W
b00000000000000000000000000000100 Y
b00000000000000000000000000000100 [
b010 \
b00000000000000000000000000000100 ]
0^
1_
b00000000000000000000000000000100 b
1h
1m
1r
1{
1#!
1%!
b01 0!
b00000000000000000000000000000100 1!
b00000000000000000000000000000100 2!
b00000000000000000000000000000100 7!
18!
1:!
b00000000000000000000000000000100 ;!
1=!
#25000
0#
03
0_
0h
0m
0r
0{
0#!
08!
0=!
#30000
1#
0&
b11 +
0/
b100011 1
b000100 2
13
06
b11 ;
0?
b100011 A
b000100 B
b00000000000000000000000000000100 C
b00000000000000000000000000000100 D
b00000000000000000000000000000100 E
b00100000000000110000000000011001 H
b10001100001000100000000000000100 I
b00010 J
b00000000000000000000000000000100 K
b00000000000000000000000000000100 P
b00000000000000000000000000010000 Q
b00000000000000000000000000000100 R
b00000000000000000000000000010000 S
b00000000000000000000000000010100 U
0W
b0000100010000000000000010000 X
b00000000000000000000000000010100 Y
b00000000000000000000000000000100 Z
b00000000000000000000000000010000 [
b00000000000000000000000000010100 ]
1_
b00000000000000000000000000010100 b
b00000000000000000000000000000100 c
b00000000000000000000000000000100 d
b00000000000000000000000000000100 g
1h
b00100000000000110000000000011001 k
1m
1r
b00000000000000000000000000000100 w
b00000000000000000000000000000100 x
b00000000000000000000000000000100 z
1{
b00000000000000000000000000000100 }
b00100000000000110000000000011001 !!
b000000001 "!
1#!
0%!
b00100000000000110000000000011001 &!
b10001100001000100000000000000100 '!
b00000000000000000000000000000100 (!
b00000000000000000000000000000100 +!
b00000000000000000000000000000100 .!
b00000000000000000000000000010000 /!
b11 0!
b00000000000000000000000000010000 1!
b00000000000000000000000000010100 2!
b00000000000000000000000000000100 3!
b00000000100010000000000000010000 4!
b00000000000000000000000000010100 7!
18!
0:!
b00000000000000000000000000010100 ;!
b00000000000000000000000000000100 <!
1=!
b00001 >!
b00010 ?!
b00010 @!
b00000000000000000000000000000100 A!
b00010 e!
b00010 h!
b00001000100000000000000100 i!
b0000100010000000000000010000 j!
b00000000000000000000000000000100 k!
b00000000000000000000000000010000 l!
b0000000000000100 m!
b00000000000000000000000000000100 n!
#35000
0#
03
0_
0h
0m
0r
0{
0#!
08!
0=!
#40000
1#
1*
b10 +
13
1:
b10 ;
b00000000000000000000000000010100 D
b00100000000000110000000000011001 F
b00000000000000000000000000010100 K
b00000000000000000000000000000000 R
b00000000000000000000000000000100 S
b00000000000000000000000000000100 U
b00000000000000000000000000000100 Y
b00000000000000000000000000000000 Z
b00000000000000000000000000000100 [
b00000000000000000000000000000100 ]
1_
b00000000000000000000000000000100 b
b00000000000000000000000000010100 c
b00000000000000000000000000010100 d
b00100000000000110000000000011001 e
b00000000000000000000000000010100 g
1h
b00100000000000110000000000011001 l
1m
1r
b00000000000000000000000000010100 x
1{
1#!
1*!
b00000000000000000000000000000000 +!
b10 0!
b00000000000000000000000000000100 1!
b00000000000000000000000000000100 2!
b00000000000000000000000000010100 3!
b00000000000000000000000000000100 7!
18!
b00000000000000000000000000000100 ;!
1=!
b00000000000000000000000000010100 A!
#45000
0#
03
0_
0h
0m
0r
0{
0#!
08!
0=!
#50000
1#
1$
0*
b00 +
b000 ,
13
14
0:
b00 ;
b000 <
b00000000000000000000000000000100 D
b00000000000000000000000000000100 K
b00000000000000000000000000000100 R
b00000000000000000000000000000000 S
1T
b00000000000000000000000000000000 U
b00000000000000000000000000000000 Y
b00000000000000000000000000000100 Z
b00000000000000000000000000000000 [
b000 \
b00000000000000000000000000000000 ]
1^
1_
b00000000000000000000000000000000 b
b00000000000000000000000000000100 c
b00000000000000000000000000000100 d
b00000000000000000000000000000100 g
1h
1m
1r
b00000000000000000000000000000100 x
1y
1{
1#!
0*!
b00000000000000000000000000000100 +!
b00 0!
b00000000000000000000000000000000 1!
b00000000000000000000000000000000 2!
b00000000000000000000000000000100 3!
b00000000000000000000000000000000 7!
18!
b00000000000000000000000000000000 ;!
1=!
b00000000000000000000000000000100 A!
#55000
0#
03
0_
0h
0m
0r
0{
0#!
08!
0=!
#60000
1#
0$
1(
1)
13
04
18
19
b00000000000000000000000000000000 D
b00100000000000110000000000011001 K
1_
b00000000000000000000000000000000 c
b00000000000000000000000000000000 d
1f
b00100000000000110000000000011001 g
1h
1m
1r
b00000000000000000000000000000000 x
0y
1{
1#!
b00000000000000000000000000000000 3!
18!
1=!
b00100000000000110000000000011001 A!
1B!
#65000
0#
03
0_
0h
0m
0r
0{
0#!
08!
0=!
#70000
1#
1&
0(
0)
b01 +
b010 ,
1/
13
16
08
09
b01 ;
b010 <
1?
b00000000000000000000000000000000 K
b00100000000000110000000000011001 M
b00000000000000000000000000000100 S
0T
b00000000000000000000000000001000 U
1W
b00000000000000000000000000001000 Y
b00000000000000000000000000000100 [
b010 \
b00000000000000000000000000001000 ]
0^
1_
b00000000000000000000000000001000 b
0f
b00000000000000000000000000000000 g
1h
1m
1r
b00100000000000110000000000011001 u
1{
1#!
1%!
b01 0!
b00000000000000000000000000000100 1!
b00000000000000000000000000001000 2!
b00000000000000000000000000001000 7!
18!
1:!
b00000000000000000000000000001000 ;!
1=!
b00000000000000000000000000000000 A!
0B!
b00100000000000110000000000011001 D!
b00100000000000110000000000011001 G!
#75000
0#
03
0_
0h
0m
0r
0{
0#!
08!
0=!
